fetch_dcos_token/fetch_dcos_token.py
fetch_dcos_token-0.9.7.dist-info/LICENSE
fetch_dcos_token-0.9.7.dist-info/METADATA
fetch_dcos_token-0.9.7.dist-info/WHEEL
fetch_dcos_token-0.9.7.dist-info/top_level.txt
fetch_dcos_token-0.9.7.dist-info/RECORD
