Metadata-Version: 2.1
Name: fetch-dcos-token
Version: 0.9.7
Summary: Simple module to get a JWT token from a DC/OS master
Home-page: https://github.com/m-dekkers/fetch_dcos_token
Author: Martijn Dekkers
Author-email: pypi@dekkers.org.uk
License: UNKNOWN
Platform: UNKNOWN
Classifier: License :: OSI Approved :: Apache Software License
Classifier: Programming Language :: Python :: 3.5
Classifier: Programming Language :: Python :: 3.6
Classifier: Programming Language :: Python :: 3.7
Requires-Dist: jwt
Requires-Dist: requests
Requires-Dist: datetime
